[
  {
    "id": "d3ef88c8-ec10-42df-b992-27b37989dbbb",
    "email": "tester-1766334819416@example.com",
    "passwordHash": "$2b$10$3hZuwVn09FvBmhWnixGqW..5MEbLEppTqECluotYM5JtGXGYhebFe",
    "displayName": "tester",
    "avatarUrl": null,
    "createdAt": 1766334819574
  },
  {
    "id": "96bd67cd-48c7-4892-a025-c2c9bdb859ba",
    "email": "test+1766338902135@example.com",
    "passwordHash": "$2b$10$ZY1W63eU23yE1gOCYiGO1OtYDT0q50w91fzv9erYiYZRFk1h8q4OC",
    "displayName": "Testy",
    "avatarUrl": null,
    "createdAt": 1766338902195
  },
  {
    "id": "e1ec7ed7-c21a-4b4c-9e42-d74c4de93044",
    "email": "test+1766342095531@example.com",
    "passwordHash": "$2b$10$wACUTeqpxrtGd42eFmn9IePcMwGElGiD0bUaVbZubWymYIZ3lVapO",
    "displayName": "Testy",
    "avatarUrl": null,
    "createdAt": 1766342095590
  },
  {
    "id": "ba8d2e9f-198c-45dc-be0c-5fba134214e6",
    "email": "test+1766342525806@example.com",
    "passwordHash": "$2b$10$rtDZJ2TnXGv/o74/9X/lKeUDVmXxgiIETFprCDi5Vo8ch4nhf3oTm",
    "displayName": "Testy",
    "avatarUrl": null,
    "createdAt": 1766342525882
  },
  {
    "id": "3c80c557-befc-4486-8d67-822c4dbdd16c",
    "email": "test+1766767809243@example.com",
    "passwordHash": "$2b$10$ixg3bDWNU83esP2Ff9IudObE7iHhxd8kQCEX/LAV9krPG1y1ayWLK",
    "displayName": "Testy",
    "avatarUrl": null,
    "createdAt": 1766767809344
  },
  {
    "id": "32731d41-1ad6-4e23-ae84-0bfe38640845",
    "email": "test+1766767824602@example.com",
    "passwordHash": "$2b$10$co2uzh3y64G/mrbOs.VkOu5u5vdA6169BWaNHCEPSHjqEyAZoEUrq",
    "displayName": "Testy",
    "avatarUrl": null,
    "createdAt": 1766767824719
  },
  {
    "id": "826f85ac-4ae5-4a8c-b9fb-fb3827c61ae1",
    "email": "test+1766767999473@example.com",
    "passwordHash": "$2b$10$tIWOcHtA9M6c0QpoAUdRTeKDqbNkVYRORCGcsnnCDs/DJT0C4VI8m",
    "displayName": "Testy",
    "avatarUrl": null,
    "createdAt": 1766767999590
  },
  {
    "id": "3a691218-27c4-4fd2-9daf-ef9e011b1202",
    "email": "test+1766768178078@example.com",
    "passwordHash": "$2b$10$vfmHRX3XXz0sMxiLSNnGcOAJx6rio1GMLadRP7xMNbkOhA/iK6mKS",
    "displayName": "Testy",
    "avatarUrl": null,
    "createdAt": 1766768178195
  },
  {
    "id": "4faebf11-35b2-4088-8a9b-7c6fabe6b8c1",
    "email": "test+1767012874488@example.com",
    "passwordHash": "$2b$10$8vhjhgvo6/OhcpQFgld8eOns1zm9dmqTtSVv27Fl/UrSC2wLBbCQe",
    "displayName": "Testy",
    "avatarUrl": null,
    "createdAt": 1767012874549
  },
  {
    "id": "3b0d5c05-01fe-401b-92f2-4bac6e52e18f",
    "email": "test+1767215966866@example.com",
    "passwordHash": "$2b$10$t0POIk64MLI4ifT4Kjek4.JjBcIBUFy5jtTgLOGKDauCn1oCkeITO",
    "displayName": "Testy",
    "avatarUrl": null,
    "createdAt": 1767215966944
  },
  {
    "id": "be6d7fb3-ee88-4e55-8d92-32b7c3118089",
    "email": "test+1767820838257@example.com",
    "passwordHash": "$2b$10$T704aTqL6Vr3rB5wt5JQx.Gr9HZb9YseI2qAkvFk30v7lO1hQ2m.6",
    "displayName": "Testy",
    "avatarUrl": null,
    "createdAt": 1767820838311
  },
  {
    "id": "6518e38c-f66f-427b-8ed4-6e0e49de947e",
    "email": "test+1768055549669@example.com",
    "passwordHash": "$2b$10$e4rD8ds1D/1stTEylgQtY.90RMAA2BWI0lOCB3P4L56RKZPrm9ybu",
    "displayName": "Testy",
    "avatarUrl": null,
    "createdAt": 1768055549723
  },
  {
    "id": "63c2c373-ab53-48b8-a340-86c1cf59994a",
    "email": "test+1768062062089@example.com",
    "passwordHash": "$2b$10$e7B8EyylKWYwefQ5GR8N0e1J7AaxG0TcwYKuT0GH6Ah7IQeCOuKDK",
    "displayName": "Testy",
    "avatarUrl": null,
    "createdAt": 1768062062145
  },
  {
    "id": "bd6e4c12-f08e-43f5-96da-4248fc1a4806",
    "email": "test+1768075692577@example.com",
    "passwordHash": "$2b$10$UhpNUTEVC96O3C1wRnefDOCqR10D/IGMPJT/.FzAmgejKogamtb5G",
    "displayName": "Testy",
    "avatarUrl": null,
    "createdAt": 1768075692633
  },
  {
    "id": "2852555f-88a9-4365-a92c-fab88a258123",
    "email": "test+1768075712901@example.com",
    "passwordHash": "$2b$10$i6vxI/DR9fp45NAsAjuwQevEYXNG7XTHokdhCXZ69pMR6I21nv8TC",
    "displayName": "Testy",
    "avatarUrl": null,
    "createdAt": 1768075712958
  },
  {
    "id": "b6e16249-5847-44ec-9f71-c6d0ef3bd5b5",
    "email": "test+1768075733932@example.com",
    "passwordHash": "$2b$10$j3G2ma/mDZ2KFswBh40oMOQ4TQc/CV2T8BaqVXsoPw.yK1G0eS.eK",
    "displayName": "Testy",
    "avatarUrl": null,
    "createdAt": 1768075733987
  },
  {
    "id": "6f1881bf-281b-4c69-8156-2de893c3d0f8",
    "email": "test+1768075755174@example.com",
    "passwordHash": "$2b$10$G4ym.35erjmlBfaD8NoJY.bqGQ8fyeomGKP4Os2v1XFyt.4lQRtMu",
    "displayName": "Testy",
    "avatarUrl": null,
    "createdAt": 1768075755228
  }
]